ncrystal_plugin_UraniumOxideData/__init__.py
ncrystal_plugin_UraniumOxideData/data/UO2_sg225_UraniumOxide_vdos1200K.ncmat
ncrystal_plugin_UraniumOxideData/data/UO2_sg225_UraniumOxide_vdos1675K.ncmat
ncrystal_plugin_UraniumOxideData/data/UO2_sg225_UraniumOxide_vdos300K.ncmat
ncrystal_plugin_UraniumOxideData/data/UO2_sg225_UraniumOxide_vdos350K.ncmat
ncrystal_plugin_UraniumOxideData/data/UO2_sg225_UraniumOxide_vdos420K.ncmat
ncrystal_plugin_UraniumOxideData/data/UO2_sg225_UraniumOxide_vdos600K.ncmat
ncrystal_plugin_UraniumOxideData/data/UO2_sg225_UraniumOxide_vdos900K.ncmat
ncrystal_plugin_UraniumOxideData-0.0.1.dist-info/LICENSE
ncrystal_plugin_UraniumOxideData-0.0.1.dist-info/METADATA
ncrystal_plugin_UraniumOxideData-0.0.1.dist-info/WHEEL
ncrystal_plugin_UraniumOxideData-0.0.1.dist-info/top_level.txt
ncrystal_plugin_UraniumOxideData-0.0.1.dist-info/RECORD
